projectspec/__init__.py
projectspec/audit.py
projectspec/cli.py
projectspec/core.py
projectspec/reconcile.py
projectspec/review.py
projectspec-0.1.1.dist-info/METADATA
projectspec-0.1.1.dist-info/WHEEL
projectspec-0.1.1.dist-info/entry_points.txt
projectspec-0.1.1.dist-info/RECORD
