Metadata-Version: 2.4
Name: projectspec
Version: 0.1.1
Summary: Machine-readable specs that link intent to code, with tooling to surface drift
Project-URL: Homepage, https://github.com/codewithcheese/projectspec
Project-URL: Documentation, https://github.com/codewithcheese/projectspec#readme
Project-URL: Repository, https://github.com/codewithcheese/projectspec
Project-URL: Issues, https://github.com/codewithcheese/projectspec/issues
Author: codewithcheese
License-Expression: MIT
Keywords: ai-agents,drift,intent,reconciliation,specification
Classifier: Development Status :: 3 - Alpha
Classifier: Environment :: Console
Classifier: Intended Audience :: Developers
Classifier: License :: OSI Approved :: MIT License
Classifier: Programming Language :: Python :: 3
Classifier: Programming Language :: Python :: 3.10
Classifier: Programming Language :: Python :: 3.11
Classifier: Programming Language :: Python :: 3.12
Classifier: Topic :: Software Development :: Quality Assurance
Requires-Python: >=3.10
Requires-Dist: pyyaml>=6.0
Requires-Dist: scriv>=1.8.0
Provides-Extra: dev
Requires-Dist: mypy; extra == 'dev'
Requires-Dist: pytest-cov; extra == 'dev'
Requires-Dist: pytest>=7.0; extra == 'dev'
Requires-Dist: ruff; extra == 'dev'
Requires-Dist: scriv[toml]; extra == 'dev'
Provides-Extra: validation
Requires-Dist: jsonschema>=4.0; extra == 'validation'
